odoo/addons/product_category_tax/README.rst
odoo/addons/product_category_tax/__init__.py
odoo/addons/product_category_tax/__manifest__.py
odoo/addons/product_category_tax/i18n/es.po
odoo/addons/product_category_tax/i18n/it.po
odoo/addons/product_category_tax/i18n/product_category_tax.pot
odoo/addons/product_category_tax/models/__init__.py
odoo/addons/product_category_tax/models/product_category.py
odoo/addons/product_category_tax/models/product_product.py
odoo/addons/product_category_tax/models/product_template.py
odoo/addons/product_category_tax/readme/CONFIGURATION.rst
odoo/addons/product_category_tax/readme/CONTRIBUTORS.md
odoo/addons/product_category_tax/readme/DESCRIPTION.md
odoo/addons/product_category_tax/readme/USAGE.md
odoo/addons/product_category_tax/static/description/icon.png
odoo/addons/product_category_tax/static/description/index.html
odoo/addons/product_category_tax/tests/__init__.py
odoo/addons/product_category_tax/tests/test_product_category_tax.py
odoo/addons/product_category_tax/views/product_category.xml
odoo/addons/product_category_tax/views/product_template.xml
odoo_addon_product_category_tax-18.0.1.0.0.4.dist-info/METADATA
odoo_addon_product_category_tax-18.0.1.0.0.4.dist-info/WHEEL
odoo_addon_product_category_tax-18.0.1.0.0.4.dist-info/top_level.txt
odoo_addon_product_category_tax-18.0.1.0.0.4.dist-info/RECORD
